{
  "completion_gap_report": {
    "generated_from": [
      "upgrade_truth_report.json",
      "live_readiness_gate.json",
      "training_orchestrator.json",
      "decision_execution_bridge.json",
      "real_api_readiness.json"
    ],
    "headline": {
      "completion_excluding_real_broker_pct": 80,
      "remaining_major_blocks_excluding_real_broker": 1,
      "real_broker_binding_present": false
    },
    "subscores": {
      "architecture_pct": 96,
      "legacy_core_pct": 95,
      "governance_pct": 92,
      "training_pct": 29,
      "execution_pct": 100,
      "paper_execution_pct": 80
    },
    "completed_excluding_real_broker": [
      "24/24 架構模組達 95+",
      "舊核心已納管進主控",
      "live readiness gate / TW market rules / execution bridge 已建立",
      "safe upgrade / checkpoint / retry / resume 已建立"
    ],
    "remaining_excluding_real_broker": [
      "AI訓練資料與模型產物仍未落地到可訓練水位"
    ],
    "detailed_flags": {
      "training_ready": false,
      "execution_payload_ready": true,
      "paper_execution_ready": true,
      "live_ready": false,
      "real_api_live_bound": false
    },
    "real_api_is_separate_track": {
      "already_reserved": [
        "broker submission contract defined",
        "callback normalization contract defined",
        "live approval workflow reserved",
        "real broker stub reserved",
        "order payload preview contract defined"
      ],
      "still_missing": [
        "broker authentication and token refresh",
        "account routing: cash / margin / short-sell",
        "market session calendar and holiday source",
        "tick size / price band / odd-lot rules",
        "broker order id mapping and idempotency key",
        "real callback receiver and persistence",
        "partial fill reconciliation against broker ledger",
        "cancel/replace semantics for each broker",
        "rate limit and retry policy by endpoint",
        "live kill-switch and operator confirmation UX"
      ]
    },
    "status": "completion_gap_mapped_v78"
  },
  "training_orchestrator": {
    "generated_at": "2026-04-08 14:57:59",
    "module_version": "v78",
    "ai_stage_enabled": false,
    "dry_run": true,
    "bootstrap": {
      "bootstrap_source": "C:\\test\\test-2026-3-22OK\\daily_decision_desk.csv",
      "registry_written": true,
      "template_written": true,
      "candidate_feature_count": 8
    },
    "dataset": {
      "exists": false,
      "rows": 0,
      "columns": [],
      "feature_count": 0,
      "label_balance": {},
      "regime_counts": {},
      "status": "missing",
      "readiness_score": 15
    },
    "models": {
      "models_dir_exists": true,
      "required_files": [
        {
          "path": "C:\\test\\test-2026-3-22OK\\models\\selected_features.pkl",
          "exists": true
        },
        {
          "path": "C:\\test\\test-2026-3-22OK\\models\\model_趨勢多頭.pkl",
          "exists": false
        },
        {
          "path": "C:\\test\\test-2026-3-22OK\\models\\model_區間盤整.pkl",
          "exists": true
        },
        {
          "path": "C:\\test\\test-2026-3-22OK\\models\\model_趨勢空頭.pkl",
          "exists": true
        }
      ],
      "existing_required_count": 3,
      "all_required_present": false,
      "readiness_score": 50
    },
    "actions": [
      {
        "stage": "ai",
        "action": "skip",
        "reason": "run_ai_stage=False"
      }
    ],
    "training_readiness_pct": 29,
    "go_for_training": false,
    "go_for_inference": true,
    "status": "training_governed"
  },
  "decision_execution_bridge": {
    "generated_at": "2026-04-08 14:58:00",
    "module_version": "v78",
    "rows_total": 3,
    "rows_with_price": 3,
    "rows_with_qty": 3,
    "rows_market_rule_passed": 3,
    "rows_market_rule_failed": 0,
    "price_source_counts": {
      "unknown": 3
    },
    "sizing_reason_counts": {
      "paper_odd_lot_min_of_risk_cap": 2,
      "strict_min_of_risk_cap": 1
    },
    "failed_tickers_preview": [],
    "missing_price_tickers": [],
    "rows_board_lot_ready": 1,
    "rows_odd_lot_ready_for_paper": 2,
    "execution_readiness_pct": 100,
    "output_path": "C:\\test\\test-2026-3-22OK\\data\\executable_order_payloads.csv",
    "price_gap_bridge_status": "price_gap_reduced",
    "status": "execution_payload_ready"
  },
  "price_gap_bridge": {
    "generated_at": "2026-04-08 14:58:00",
    "module_version": "v73",
    "scanned_csv_count": 9,
    "scanned_csv_success_count": 3,
    "candidate_rows": 4,
    "required_tickers": 3,
    "matched_tickers": 3,
    "missing_tickers": [],
    "price_scan_dirs": [
      "C:\\test\\test-2026-3-22OK",
      "C:\\test\\test-2026-3-22OK\\data"
    ],
    "source_mount_dirs": [],
    "manual_override_path": "C:\\test\\test-2026-3-22OK\\data\\manual_price_snapshot_overrides.csv",
    "candidates_path": "C:\\test\\test-2026-3-22OK\\data\\auto_price_snapshot_candidates.csv",
    "manual_template_path": "C:\\test\\test-2026-3-22OK\\data\\manual_price_snapshot_template.csv",
    "status": "price_gap_reduced"
  },
  "config": {
    "package_version": "v78",
    "source_mount_dirs": [],
    "price_scan_dirs": [
      "C:\\test\\test-2026-3-22OK",
      "C:\\test\\test-2026-3-22OK\\data"
    ],
    "history_scan_dirs": [
      "C:\\test\\test-2026-3-22OK",
      "C:\\test\\test-2026-3-22OK\\data"
    ]
  }
}