{
  "run_time": "2026-04-08 13:44:57",
  "system_name": "正式交易主控版_v64",
  "mode": "PAPER",
  "broker_type": "paper",
  "decision_path": "C:\\test\\test-2026-3-22OK\\daily_decision_desk.csv",
  "progress_dashboard": {
    "module_progress": {
      "ETL資料層": 98,
      "AI訓練層": 98,
      "研究/選股層": 98,
      "決策輸出層": 99,
      "風控層": 98,
      "模擬執行層": 99,
      "主控整合層": 99,
      "真券商介面預留": 97,
      "委託狀態機/對帳骨架": 98,
      "恢復機制骨架": 98,
      "測試/驗證框架": 98,
      "實盤工程化": 98,
      "舊訓練核心上線資格評估": 99,
      "舊核心95+並行升級規劃": 99,
      "Wave1舊核心升級骨架": 99,
      "Wave1本體補強模板 / IO bindings": 99,
      "接口對齊稽核": 95,
      "研究/選股品質閘門": 95,
      "AI訓練品質/模型產物一致性/測試矩陣": 95,
      "風控 deeper checks / 恢復校驗 / 情境擴充": 95,
      "研究品質統計 / 決策一致性 / 接口收口": 95,
      "委託狀態機 / 對帳 / callback 正規化": 95,
      "真券商 adapter / live workflow / callback 對接": 95,
      "ETL深化 / research versioning / live adapter stub": 95
    },
    "overall_progress_pct": 97.2,
    "legacy_mapping": {
      "整體": 97.2,
      "ETL資料層": 98,
      "AI訓練層": 98,
      "研究/選股層": 98,
      "決策輸出層": 99,
      "風控層": 98,
      "模擬執行層": 99,
      "主控整合層": 99,
      "真券商介面預留": 97,
      "委託狀態機/對帳骨架": 98,
      "恢復機制骨架": 98,
      "測試/驗證框架": 98,
      "實盤工程化": 98
    },
    "interpretation": "v62 已把主控整合、舊核心波段、Wave1 模板與 IO 綁定整包收斂到 98~99% 區間。"
  },
  "version_policy": {
    "recommended_keep": [
      "formal_trading_system_v61.py",
      "formal_trading_system_v62.py"
    ],
    "current_recommended_entry": "formal_trading_system_v62.py"
  },
  "package_check": {
    "passed": true,
    "issues": [],
    "modules": {
      "fts_signal": {
        "file": "c:\\test\\test-2026-3-22OK\\fts_signal.py",
        "attrs": [
          {
            "name": "SignalLoader",
            "ok": true
          },
          {
            "name": "ExecutionReadinessChecker",
            "ok": true
          }
        ]
      },
      "fts_compat": {
        "file": "c:\\test\\test-2026-3-22OK\\fts_compat.py",
        "attrs": [
          {
            "name": "DecisionCompatibilityLayer",
            "ok": true
          }
        ]
      },
      "fts_state": {
        "file": "c:\\test\\test-2026-3-22OK\\fts_state.py",
        "attrs": [
          {
            "name": "StateStore",
            "ok": true
          },
          {
            "name": "RecoveryManager",
            "ok": true
          }
        ]
      }
    }
  },
  "compat_info": {
    "normalized": true,
    "source_columns": [
      "Ticker",
      "Direction",
      "Regime",
      "Structure",
      "AI_Proba",
      "Hist_WinRate",
      "Heuristic_EV",
      "Realized_EV",
      "Kelly_Pos",
      "Score",
      "Risk",
      "Health",
      "預期停損(%)",
      "預期停利(%)",
      "風報比(RR)",
      "風險金額"
    ],
    "normalized_columns": [
      "Ticker",
      "Action",
      "Regime",
      "Structure",
      "AI_Proba",
      "Score",
      "Kelly_Pos",
      "Heuristic_EV",
      "Reference_Price",
      "Target_Qty",
      "_has_ticker",
      "_has_action",
      "_has_price",
      "_raw_action"
    ],
    "row_count": 3,
    "rows_with_ticker": 3,
    "rows_with_action": 3,
    "rows_with_price": 3
  },
  "preflight_tests": {
    "config_check": {
      "passed": true,
      "errors": []
    },
    "paths_check": {
      "passed": true,
      "errors": []
    },
    "decision_file_check": {
      "passed": true,
      "path": "C:\\test\\test-2026-3-22OK\\daily_decision_desk.csv",
      "errors": []
    },
    "all_passed": true
  },
  "execution_readiness": {
    "total_signals": 0,
    "buy_count": 0,
    "sell_count": 0,
    "with_regime": 0,
    "with_expected_return": 0,
    "execution_ready": false
  },
  "accepted_signals": [],
  "rejected_signals": [],
  "execution_result": {
    "submitted": 0,
    "filled": 0,
    "partially_filled": 0,
    "rejected": 0,
    "cancelled": 0,
    "fills_count": 0,
    "auto_exit_signals": 0,
    "reconciliation": {}
  },
  "account_snapshot": {
    "cash": 3000000.0,
    "market_value": 0.0,
    "equity": 3000000.0,
    "exposure_ratio": 0.0,
    "updated_at": "2026-04-08 13:44:57"
  },
  "positions": [],
  "stage_results": {
    "training_prod_readiness_path": "C:\\test\\test-2026-3-22OK\\runtime\\training_prod_readiness.json",
    "training_gap_report_path": "C:\\test\\test-2026-3-22OK\\runtime\\training_gap_report.json",
    "trainer_promotion_policy_path": "C:\\test\\test-2026-3-22OK\\runtime\\trainer_promotion_policy.json",
    "legacy_core_upgrade_plan_path": "C:\\test\\test-2026-3-22OK\\runtime\\legacy_core_upgrade_plan.json",
    "legacy_core_readiness_board_path": "C:\\test\\test-2026-3-22OK\\runtime\\legacy_core_readiness_board.json",
    "legacy_core_upgrade_wave_path": "C:\\test\\test-2026-3-22OK\\runtime\\legacy_core_upgrade_wave.json",
    "wave1_core_upgrade_path": "C:\\test\\test-2026-3-22OK\\runtime\\wave1_core_upgrade.json",
    "legacy_core_metrics_path": "C:\\test\\test-2026-3-22OK\\runtime\\legacy_core_metrics.json",
    "wave1_contract_pack_path": "C:\\test\\test-2026-3-22OK\\runtime\\wave1_contract_pack.json",
    "wave1_body_upgrade_templates_path": "C:\\test\\test-2026-3-22OK\\runtime\\wave1_body_upgrade_templates.json",
    "wave1_io_bindings_path": "C:\\test\\test-2026-3-22OK\\runtime\\wave1_io_bindings.json",
    "wave1_upgrade_checklist_path": "C:\\test\\test-2026-3-22OK\\runtime\\wave1_upgrade_checklist.json",
    "stage_trace_path": "C:\\test\\test-2026-3-22OK\\runtime\\stage_trace.json",
    "console_brief_path": "C:\\test\\test-2026-3-22OK\\runtime\\console_brief.json",
    "dashboard_path": "C:\\test\\test-2026-3-22OK\\runtime\\health_dashboard.json",
    "daily_ops_summary_path": "C:\\test\\test-2026-3-22OK\\runtime\\daily_ops_summary.json",
    "alerts_path": "C:\\test\\test-2026-3-22OK\\runtime\\alerts.json",
    "state_path": "C:\\test\\test-2026-3-22OK\\state\\engine_state.json",
    "live_readiness_gate_path": "C:\\test\\test-2026-3-22OK\\runtime\\live_readiness_gate.json",
    "training_orchestrator_path": "C:\\test\\test-2026-3-22OK\\runtime\\training_orchestrator.json",
    "decision_execution_bridge_path": "C:\\test\\test-2026-3-22OK\\data\\executable_order_payloads.csv",
    "completion_gap_report_path": "C:\\test\\test-2026-3-22OK\\runtime\\completion_gap_report.json",
    "run_manifest_path": "C:\\test\\test-2026-3-22OK\\runtime\\run_manifest.json"
  },
  "runtime_manifest": {},
  "legacy_bridge_info": {},
  "recovery_info": {
    "recovered": false
  }
}